.gitignore
MANIFEST.in
README.md
README.rst
TODO
setup.py
bin/translate_passage
example_scripts/example_flupan.py
example_scripts/flupan.log
flupan.egg-info/PKG-INFO
flupan.egg-info/SOURCES.txt
flupan.egg-info/dependency_links.txt
flupan.egg-info/top_level.txt
src/__init__.py
src/passage_interpreter.py
src/tables/__init__.py
src/tables/coerce_format.txt
src/tables/generate_passage_table.py
src/tables/nonstandard_passages_input.txt
src/tables/passage_lookup.txt
src/tables/unknown_passages_input.txt
tests/.~lock.test_conversion1.txt#
tests/__init__.py
tests/__init__.pyc
tests/output_test_passageIDs1.txt
tests/output_test_passageIDs2.txt
tests/passage_interpreter.out
tests/passage_interpreter_test.py
tests/passage_interpreter_test.pyc
tests/reduced_gisaid_sequences.fasta
tests/test_passageIDs1.txt
tests/test_passageIDs2.txt
tests/test_unformatted_passage_IDs.txt
tests/flupan.egg-info/PKG-INFO
tests/flupan.egg-info/SOURCES.txt
tests/flupan.egg-info/dependency_links.txt
tests/flupan.egg-info/top_level.txt