Metadata-Version: 1.0
Name: flupan
Version: 0.1.1
Summary: Python library to parse influenza passaging annotations
Home-page: http://github.com/clauswilke/flupan
Author: Claire D. McWhite
Author-email: claire.mcwhite@utexas.edu
License: MIT
Platform: UNKNOWN
